py_mpworker/__init__.py
py_mpworker-1.1.0.dist-info/LICENSE
py_mpworker-1.1.0.dist-info/METADATA
py_mpworker-1.1.0.dist-info/WHEEL
py_mpworker-1.1.0.dist-info/top_level.txt
py_mpworker-1.1.0.dist-info/RECORD
